asteria/__init__.py
asteria/__main__.py
asteria/constants.py
asteria/driver.py
asteria/metrics.py
asteria/scales.py
asteria/utils.py
asteria/instruments/__init__.py
asteria/instruments/morse.py
asteria_openrgb-0.2.0.dist-info/METADATA
asteria_openrgb-0.2.0.dist-info/WHEEL
asteria_openrgb-0.2.0.dist-info/entry_points.txt
asteria_openrgb-0.2.0.dist-info/licenses/LICENSE
asteria_openrgb-0.2.0.dist-info/RECORD
