Metadata-Version: 2.1
Name: asteria-openrgb
Version: 0.2.0
Summary: A framework to automatically control LEDs via OpenRGB
Project-URL: Homepage, https://gitlab.com/JoshWVS/asteria
Author-email: Joshua Simpson <josh@simpsonian.ca>
License:                     GNU AFFERO GENERAL PUBLIC LICENSE
License-File: LICENSE
Classifier: License :: OSI Approved :: GNU Affero General Public License v3
Classifier: Programming Language :: Python :: 3
Requires-Python: >=3
Requires-Dist: openrgb-python>0.2
Requires-Dist: tomli>2
Provides-Extra: test
Requires-Dist: pytest>7; extra == 'test'
